scratchtool/__init__.py
scratchtool/_cloud_class.py
scratchtool/_login_class.py
scratchtool/_project_class.py
scratchtool/_user_class.py
scratchtool/login_class.py
scratchtool/project_class.py
scratchtool/user_class.py
scratchtool-1.3.1.dist-info/METADATA
scratchtool-1.3.1.dist-info/WHEEL
scratchtool-1.3.1.dist-info/entry_points.txt
scratchtool-1.3.1.dist-info/top_level.txt
scratchtool-1.3.1.dist-info/RECORD
