Metadata-Version: 2.1
Name: scratchtool
Version: 1.3.1
Summary: A package for working with Scratch data.
Home-page: https://github.com/itijuku/scratchtool
Author: itijiku
Classifier: Programming Language :: Python :: 3
Classifier: License :: OSI Approved :: MIT License
Classifier: Operating System :: OS Independent
Requires-Python: >=3.6
Requires-Dist: requests>=2.31.0
Requires-Dist: beautifulsoup4>=4.12.3
Requires-Dist: websockets
